{"is_source_file": false, "format": "", "description": "", "external_files": [], "external_methods": [], "published": [], "classes": [], "methods": [], "calls": [], "search-terms": ["SQLite Schema", "fleet-management", "database schema", "tables", "relations"], "state": 2, "file_id": 81, "knowledge_revision": 207, "git_revision": "", "hash": "d8588aeca3e495a3e1a07a8f30c611a5", "format-version": 4, "code-base-name": "fleetease_android_app", "filename": "fleetease_android_app/SQLITE_SCHEMA.md", "revision_history": [{"207": ""}]}