{"is_source_file": false, "format": "", "description": "", "external_files": [], "external_methods": [], "published": [], "classes": [], "methods": [], "calls": [], "search-terms": [], "state": 2, "file_id": 66, "knowledge_revision": 148, "git_revision": "25231cbc07206352e9145b6e9ac574b2648deae5", "hash": "cd24c481a2af96a4e4c286a49a20e8e0", "format-version": 4, "code-base-name": "fleetease_android_app", "filename": "fleetease_android_app/.dart_tool/package_config.json", "revision_history": [{"148": "25231cbc07206352e9145b6e9ac574b2648deae5"}]}